[{"geom":[50.265723865055,2.7985687314237997],"prix_valeur":1.935,"reg_name":"Hauts-de-France","com_code":"62099","dep_name":"Pas-de-Calais","adresse":"rue Bleuets","prix_nom":"SP95","com_name":"Beaurains","ville":"BEAURAINS","com_arm_name":"Beaurains","reg_code":"32","services_service":"Vente de gaz domestique (Butane, Propane)//DAB (Distributeur automatique de billets)","com_arm_code":"62099","epci_code":"200033579","dep_code":"62","cp":"62217","id":"62217001","prix_id":"2","pop":"R","epci_name":"CU d'Arras","prix_maj":"2023-04-19T12:45:36Z","horaires_automate_24_24":"Non"},{"geom":[50.265723865055,2.7985687314237997],"prix_valeur":1.71,"reg_name":"Hauts-de-France","com_code":"62099","dep_name":"Pas-de-Calais","adresse":"rue Bleuets","prix_nom":"Gazole","com_name":"Beaurains","ville":"BEAURAINS","com_arm_name":"Beaurains","reg_code":"32","services_service":"Vente de gaz domestique (Butane, Propane)//DAB (Distributeur automatique de billets)","com_arm_code":"62099","epci_code":"200033579","dep_code":"62","cp":"62217","id":"62217001","prix_id":"1","pop":"R","epci_name":"CU d'Arras","prix_maj":"2023-04-19T12:45:35Z","horaires_automate_24_24":"Non"},{"geom":[50.265723865055,2.7985687314237997],"prix_valeur":1.976,"reg_name":"Hauts-de-France","com_code":"62099","dep_name":"Pas-de-Calais","adresse":"rue Bleuets","prix_nom":"SP98","com_name":"Beaurains","ville":"BEAURAINS","com_arm_name":"Beaurains","reg_code":"32","services_service":"Vente de gaz domestique (Butane, Propane)//DAB (Distributeur automatique de billets)","com_arm_code":"62099","epci_code":"200033579","dep_code":"62","cp":"62217","id":"62217001","prix_id":"6","pop":"R","epci_name":"CU d'Arras","prix_maj":"2023-04-19T12:45:36Z","horaires_automate_24_24":"Non"}]