[{"geom":[47.07224,5.41392],"prix_valeur":1.099,"reg_name":"Bourgogne-Franche-Comté","com_code":"39189","dep_name":"Jura","adresse":"Place du 1er mai","prix_nom":"E85","com_name":"Damparis","ville":"DAMPARIS","com_arm_name":"Damparis","reg_code":"27","services_service":"Vente de gaz domestique (Butane, Propane)//DAB (Distributeur automatique de billets)","com_arm_code":"39189","epci_code":"200010650","dep_code":"39","cp":"39500","id":"39500006","prix_id":"3","pop":"R","epci_name":"CA du Grand Dole","prix_maj":"2023-02-09T12:59:14Z","horaires_automate_24_24":"Non","name":"INTERMARCHE","brand":"Intermarché Contact","shortage":["GPLc","SP95"]},{"geom":[47.07224,5.41392],"prix_valeur":1.919,"reg_name":"Bourgogne-Franche-Comté","com_code":"39189","dep_name":"Jura","adresse":"Place du 1er mai","prix_nom":"SP98","com_name":"Damparis","ville":"DAMPARIS","com_arm_name":"Damparis","reg_code":"27","services_service":"Vente de gaz domestique (Butane, Propane)//DAB (Distributeur automatique de billets)","com_arm_code":"39189","epci_code":"200010650","dep_code":"39","cp":"39500","id":"39500006","prix_id":"6","pop":"R","epci_name":"CA du Grand Dole","prix_maj":"2023-02-16T10:00:36Z","horaires_automate_24_24":"Non","name":"INTERMARCHE","brand":"Intermarché Contact","shortage":["GPLc","SP95"]},{"geom":[47.048889,5.429444],"reg_name":"Bourgogne-Franche-Comté","prix_valeur":2.016,"com_code":"39189","dep_name":"Jura","horaires":"{\"@automate-24-24\": \"\", \"jour\": [{\"@id\": \"1\", \"@nom\": \"Lundi\", \"@ferme\": \"1\"}, {\"@id\": \"2\", \"@nom\": \"Mardi\", \"@ferme\": \"1\"}, {\"@id\": \"3\", \"@nom\": \"Mercredi\", \"@ferme\": \"1\"}, {\"@id\": \"4\", \"@nom\": \"Jeudi\", \"@ferme\": \"1\"}, {\"@id\": \"5\", \"@nom\": \"Vendredi\", \"@ferme\": \"1\"}, {\"@id\": \"6\", \"@nom\": \"Samedi\", \"@ferme\": \"1\"}, {\"@id\": \"7\", \"@nom\": \"Dimanche\", \"@ferme\": \"1\"}]}","adresse":"ROUTE NATIONALE 73","prix_nom":"Gazole","com_name":"Damparis","ville":"DAMPARIS","com_arm_name":"Damparis","reg_code":"27","services_service":"Piste poids lourds//Vente d'additifs carburants","dep_code":"39","com_arm_code":"39189","epci_code":"200010650","cp":"39500","id":"39500007","prix_id":"1","epci_name":"CA du Grand Dole","pop":"R","prix_maj":"2023-03-01T00:00:00Z","horaires_automate_24_24":"Non"},{"geom":[47.07224,5.41392],"prix_valeur":1.819,"reg_name":"Bourgogne-Franche-Comté","com_code":"39189","dep_name":"Jura","adresse":"Place du 1er mai","prix_nom":"E10","com_name":"Damparis","ville":"DAMPARIS","com_arm_name":"Damparis","reg_code":"27","services_service":"Vente de gaz domestique (Butane, Propane)//DAB (Distributeur automatique de billets)","com_arm_code":"39189","epci_code":"200010650","dep_code":"39","cp":"39500","id":"39500006","prix_id":"5","pop":"R","epci_name":"CA du Grand Dole","prix_maj":"2023-02-23T12:27:56Z","horaires_automate_24_24":"Non","name":"INTERMARCHE","brand":"Intermarché Contact","shortage":["GPLc","SP95"]},{"geom":[47.07224,5.41392],"prix_valeur":1.799,"reg_name":"Bourgogne-Franche-Comté","com_code":"39189","dep_name":"Jura","adresse":"Place du 1er mai","prix_nom":"Gazole","com_name":"Damparis","ville":"DAMPARIS","com_arm_name":"Damparis","reg_code":"27","services_service":"Vente de gaz domestique (Butane, Propane)//DAB (Distributeur automatique de billets)","com_arm_code":"39189","epci_code":"200010650","dep_code":"39","cp":"39500","id":"39500006","prix_id":"1","pop":"R","epci_name":"CA du Grand Dole","prix_maj":"2023-02-23T12:27:56Z","horaires_automate_24_24":"Non","name":"INTERMARCHE","brand":"Intermarché Contact","shortage":["GPLc","SP95"]}]