[{"geom":[44.76076,5.35682],"prix_valeur":1.879,"reg_name":"Auvergne-Rhône-Alpes","com_code":"26113","dep_name":"Drôme","adresse":"Route de la résistance Conches et Chamarges","prix_nom":"SP95","com_name":"Die","ville":"Die","com_arm_name":"Die","reg_code":"84","services_service":"Vente de gaz domestique (Butane, Propane)//DAB (Distributeur automatique de billets)","com_arm_code":"26113","epci_code":"242600534","dep_code":"26","cp":"26150","id":"26150001","prix_id":"2","pop":"R","epci_name":"CC du Diois","prix_maj":"2023-02-10T08:39:15Z","horaires_automate_24_24":"Non"},{"geom":[44.76076,5.35682],"prix_valeur":1.921,"reg_name":"Auvergne-Rhône-Alpes","com_code":"26113","dep_name":"Drôme","adresse":"Route de la résistance Conches et Chamarges","prix_nom":"SP98","com_name":"Die","ville":"Die","com_arm_name":"Die","reg_code":"84","services_service":"Vente de gaz domestique (Butane, Propane)//DAB (Distributeur automatique de billets)","com_arm_code":"26113","epci_code":"242600534","dep_code":"26","cp":"26150","id":"26150001","prix_id":"6","pop":"R","epci_name":"CC du Diois","prix_maj":"2023-02-10T08:39:16Z","horaires_automate_24_24":"Non"}]