[{"geom":[47.09,-1.611],"prix_valeur":1.669,"reg_name":"Pays de la Loire","com_code":"44041","dep_name":"Loire-Atlantique","adresse":"78 Grand'Rue","prix_nom":"Gazole","com_name":"La Chevrolière","ville":"La Chevrolière","com_arm_name":"La Chevrolière","reg_code":"52","services_service":"Vente de gaz domestique (Butane, Propane)//DAB (Distributeur automatique de billets)","com_arm_code":"44041","epci_code":"244400438","dep_code":"44","cp":"44118","id":"44118003","prix_id":"1","pop":"R","epci_name":"CC Grand Lieu Communauté","prix_maj":"2023-05-25T09:05:55Z","horaires_automate_24_24":"Non","name":"CARREFOUR Contact","brand":"Carrefour Contact","shortage":["E85","GPLc","E10"]},{"geom":[47.09,-1.611],"prix_valeur":1.889,"reg_name":"Pays de la Loire","com_code":"44041","dep_name":"Loire-Atlantique","adresse":"78 Grand'Rue","prix_nom":"SP95","com_name":"La Chevrolière","ville":"La Chevrolière","com_arm_name":"La Chevrolière","reg_code":"52","services_service":"Vente de gaz domestique (Butane, Propane)//DAB (Distributeur automatique de billets)","com_arm_code":"44041","epci_code":"244400438","dep_code":"44","cp":"44118","id":"44118003","prix_id":"2","pop":"R","epci_name":"CC Grand Lieu Communauté","prix_maj":"2023-05-25T09:05:55Z","horaires_automate_24_24":"Non","name":"CARREFOUR Contact","brand":"Carrefour Contact","shortage":["E85","GPLc","E10"]}]