[{"geom":[46.5400788102,0.40296038313800003],"prix_valeur":1.959,"reg_name":"Nouvelle-Aquitaine","com_code":"86157","dep_name":"Vienne","adresse":"ZAE DE BEAUBATON","prix_nom":"Gazole","com_name":"Mignaloux-Beauvoir","ville":"MIGNALOUX-BEAUVOIR","com_arm_name":"Mignaloux-Beauvoir","reg_code":"75","services_service":"Boutique alimentaire//Boutique non alimentaire//Restauration à emporter//Vente de gaz domestique (Butane, Propane)//DAB (Distributeur automatique de billets)","com_arm_code":"86157","epci_code":"200069854","dep_code":"86","cp":"86550","id":"86550001","prix_id":"1","pop":"R","epci_name":"CU du Grand Poitiers","prix_maj":"2023-01-25T11:47:55Z","horaires_automate_24_24":"Non"}]