[{"geom":[47.90027,-2.83932],"prix_valeur":1.809,"reg_name":"Bretagne","com_code":"56140","dep_name":"Morbihan","adresse":"Giratoire de Kérabuse","prix_nom":"SP95","com_name":"Moréac","ville":"Moréac","com_arm_name":"Moréac","reg_code":"53","com_arm_code":"56140","epci_code":"200096683","dep_code":"56","cp":"56500","id":"56500005","prix_id":"2","pop":"R","epci_name":"CC Centre Morbihan Communauté","prix_maj":"2023-11-17T08:22:30Z","horaires_automate_24_24":"Non","name":"LECLERC MOREAC","brand":"Leclerc","shortage":["SP98","GPLc"]},{"geom":[47.90027,-2.83932],"prix_valeur":1.779,"reg_name":"Bretagne","com_code":"56140","dep_name":"Morbihan","adresse":"Giratoire de Kérabuse","prix_nom":"Gazole","com_name":"Moréac","ville":"Moréac","com_arm_name":"Moréac","reg_code":"53","com_arm_code":"56140","epci_code":"200096683","dep_code":"56","cp":"56500","id":"56500005","prix_id":"1","pop":"R","epci_name":"CC Centre Morbihan Communauté","prix_maj":"2023-11-15T13:41:38Z","horaires_automate_24_24":"Non","name":"LECLERC MOREAC","brand":"Leclerc","shortage":["SP98","GPLc"]},{"geom":[47.90027,-2.83932],"prix_valeur":1.769,"reg_name":"Bretagne","com_code":"56140","dep_name":"Morbihan","adresse":"Giratoire de Kérabuse","prix_nom":"E10","com_name":"Moréac","ville":"Moréac","com_arm_name":"Moréac","reg_code":"53","com_arm_code":"56140","epci_code":"200096683","dep_code":"56","cp":"56500","id":"56500005","prix_id":"5","pop":"R","epci_name":"CC Centre Morbihan Communauté","prix_maj":"2023-11-17T08:22:30Z","horaires_automate_24_24":"Non","name":"LECLERC MOREAC","brand":"Leclerc","shortage":["SP98","GPLc"]}]