[{"geom":[44.84071,2.6647],"prix_valeur":1.89,"reg_name":"Occitanie","com_code":"12164","dep_name":"Aveyron","adresse":"Avenue de Brommat","prix_nom":"Gazole","com_name":"Mur-de-Barrez","ville":"Mur-de-Barrez","com_arm_name":"Mur-de-Barrez","reg_code":"76","services_service":"Carburant additivé//DAB (Distributeur automatique de billets)","com_arm_code":"12164","epci_code":"200067171","dep_code":"12","cp":"12600","id":"12600002","prix_id":"1","pop":"R","epci_name":"CC Aubrac,Carladez et Viadène","prix_maj":"2023-08-11T09:41:31Z","horaires_automate_24_24":"Non"},{"geom":[44.837,2.663],"prix_valeur":1.895,"reg_name":"Occitanie","com_code":"12164","dep_name":"Aveyron","adresse":"Route de Lacroix Barrez","prix_nom":"Gazole","com_name":"Mur-de-Barrez","ville":"MUR-DE-BARREZ","com_arm_name":"Mur-de-Barrez","reg_code":"76","services_service":"DAB (Distributeur automatique de billets)","com_arm_code":"12164","epci_code":"200067171","dep_code":"12","cp":"12600","id":"12600001","prix_id":"1","pop":"R","epci_name":"CC Aubrac,Carladez et Viadène","prix_maj":"2023-08-11T19:16:26Z","horaires_automate_24_24":"Non"},{"geom":[44.837,2.663],"prix_valeur":2.018,"reg_name":"Occitanie","com_code":"12164","dep_name":"Aveyron","adresse":"Route de Lacroix Barrez","prix_nom":"SP98","com_name":"Mur-de-Barrez","ville":"MUR-DE-BARREZ","com_arm_name":"Mur-de-Barrez","reg_code":"76","services_service":"DAB (Distributeur automatique de billets)","com_arm_code":"12164","epci_code":"200067171","dep_code":"12","cp":"12600","id":"12600001","prix_id":"6","pop":"R","epci_name":"CC Aubrac,Carladez et Viadène","prix_maj":"2023-08-05T10:42:43Z","horaires_automate_24_24":"Non"},{"geom":[44.84071,2.6647],"prix_valeur":1.99,"reg_name":"Occitanie","com_code":"12164","dep_name":"Aveyron","adresse":"Avenue de Brommat","prix_nom":"SP95","com_name":"Mur-de-Barrez","ville":"Mur-de-Barrez","com_arm_name":"Mur-de-Barrez","reg_code":"76","services_service":"Carburant additivé//DAB (Distributeur automatique de billets)","com_arm_code":"12164","epci_code":"200067171","dep_code":"12","cp":"12600","id":"12600002","prix_id":"2","pop":"R","epci_name":"CC Aubrac,Carladez et Viadène","prix_maj":"2023-08-11T09:41:31Z","horaires_automate_24_24":"Non"},{"geom":[44.837,2.663],"prix_valeur":1.997,"reg_name":"Occitanie","com_code":"12164","dep_name":"Aveyron","adresse":"Route de Lacroix Barrez","prix_nom":"SP95","com_name":"Mur-de-Barrez","ville":"MUR-DE-BARREZ","com_arm_name":"Mur-de-Barrez","reg_code":"76","services_service":"DAB (Distributeur automatique de billets)","com_arm_code":"12164","epci_code":"200067171","dep_code":"12","cp":"12600","id":"12600001","prix_id":"2","pop":"R","epci_name":"CC Aubrac,Carladez et Viadène","prix_maj":"2023-08-01T07:09:08Z","horaires_automate_24_24":"Non"},{"geom":[44.84071,2.6647],"prix_valeur":2.01,"reg_name":"Occitanie","com_code":"12164","dep_name":"Aveyron","adresse":"Avenue de Brommat","prix_nom":"SP98","com_name":"Mur-de-Barrez","ville":"Mur-de-Barrez","com_arm_name":"Mur-de-Barrez","reg_code":"76","services_service":"Carburant additivé//DAB (Distributeur automatique de billets)","com_arm_code":"12164","epci_code":"200067171","dep_code":"12","cp":"12600","id":"12600002","prix_id":"6","pop":"R","epci_name":"CC Aubrac,Carladez et Viadène","prix_maj":"2023-08-11T09:41:31Z","horaires_automate_24_24":"Non"}]