[{"geom":[47.487,-1.24],"reg_name":"Pays de la Loire","prix_valeur":1.719,"com_code":"44118","dep_name":"Loire-Atlantique","horaires":"{\"@automate-24-24\": \"1\", \"jour\": [{\"@id\": \"1\", \"@nom\": \"Lundi\", \"@ferme\": \"\"}, {\"@id\": \"2\", \"@nom\": \"Mardi\", \"@ferme\": \"\"}, {\"@id\": \"3\", \"@nom\": \"Mercredi\", \"@ferme\": \"\"}, {\"@id\": \"4\", \"@nom\": \"Jeudi\", \"@ferme\": \"\"}, {\"@id\": \"5\", \"@nom\": \"Vendredi\", \"@ferme\": \"\"}, {\"@id\": \"6\", \"@nom\": \"Samedi\", \"@ferme\": \"\"}, {\"@id\": \"7\", \"@nom\": \"Dimanche\", \"@ferme\": \"\"}]}","adresse":"23 rue des chenes","prix_nom":"Gazole","com_name":"Pannecé","ville":"Riaille","com_arm_name":"Pannecé","reg_code":"52","services_service":"Vente de gaz domestique (Butane, Propane)//Automate CB 24/24//DAB (Distributeur automatique de billets)","dep_code":"44","com_arm_code":"44118","epci_code":"244400552","cp":"44440","id":"44390004","prix_id":"1","epci_name":"CC du Pays d'Ancenis","pop":"R","prix_maj":"2024-01-23T11:45:11Z","horaires_automate_24_24":"Oui"},{"geom":[47.487,-1.24],"reg_name":"Pays de la Loire","prix_valeur":1.819,"com_code":"44118","dep_name":"Loire-Atlantique","horaires":"{\"@automate-24-24\": \"1\", \"jour\": [{\"@id\": \"1\", \"@nom\": \"Lundi\", \"@ferme\": \"\"}, {\"@id\": \"2\", \"@nom\": \"Mardi\", \"@ferme\": \"\"}, {\"@id\": \"3\", \"@nom\": \"Mercredi\", \"@ferme\": \"\"}, {\"@id\": \"4\", \"@nom\": \"Jeudi\", \"@ferme\": \"\"}, {\"@id\": \"5\", \"@nom\": \"Vendredi\", \"@ferme\": \"\"}, {\"@id\": \"6\", \"@nom\": \"Samedi\", \"@ferme\": \"\"}, {\"@id\": \"7\", \"@nom\": \"Dimanche\", \"@ferme\": \"\"}]}","adresse":"23 rue des chenes","prix_nom":"SP98","com_name":"Pannecé","ville":"Riaille","com_arm_name":"Pannecé","reg_code":"52","services_service":"Vente de gaz domestique (Butane, Propane)//Automate CB 24/24//DAB (Distributeur automatique de billets)","dep_code":"44","com_arm_code":"44118","epci_code":"244400552","cp":"44440","id":"44390004","prix_id":"6","epci_name":"CC du Pays d'Ancenis","pop":"R","prix_maj":"2024-01-23T11:45:12Z","horaires_automate_24_24":"Oui"},{"geom":[47.487,-1.24],"reg_name":"Pays de la Loire","prix_valeur":1.779,"com_code":"44118","dep_name":"Loire-Atlantique","horaires":"{\"@automate-24-24\": \"1\", \"jour\": [{\"@id\": \"1\", \"@nom\": \"Lundi\", \"@ferme\": \"\"}, {\"@id\": \"2\", \"@nom\": \"Mardi\", \"@ferme\": \"\"}, {\"@id\": \"3\", \"@nom\": \"Mercredi\", \"@ferme\": \"\"}, {\"@id\": \"4\", \"@nom\": \"Jeudi\", \"@ferme\": \"\"}, {\"@id\": \"5\", \"@nom\": \"Vendredi\", \"@ferme\": \"\"}, {\"@id\": \"6\", \"@nom\": \"Samedi\", \"@ferme\": \"\"}, {\"@id\": \"7\", \"@nom\": \"Dimanche\", \"@ferme\": \"\"}]}","adresse":"23 rue des chenes","prix_nom":"SP95","com_name":"Pannecé","ville":"Riaille","com_arm_name":"Pannecé","reg_code":"52","services_service":"Vente de gaz domestique (Butane, Propane)//Automate CB 24/24//DAB (Distributeur automatique de billets)","dep_code":"44","com_arm_code":"44118","epci_code":"244400552","cp":"44440","id":"44390004","prix_id":"2","epci_name":"CC du Pays d'Ancenis","pop":"R","prix_maj":"2024-01-23T11:45:11Z","horaires_automate_24_24":"Oui"}]