[{"geom":[49.11719,7.10084],"prix_valeur":0.997,"reg_name":"Grand Est","com_code":"57631","dep_name":"Moselle","adresse":"Route de Bitche","prix_nom":"GPLc","com_name":"Sarreguemines","ville":"SARREGUEMINES","com_arm_name":"Sarreguemines","reg_code":"44","services_service":"Toilettes publiques//Boutique alimentaire//Boutique non alimentaire//Restauration à emporter//Restauration sur place//Bar//Station de gonflage//Location de véhicule//Piste poids lourds//Espace bébé//Vente de gaz domestique (Butane, Propane)//DAB (Distributeur automatique de billets)","com_arm_code":"57631","epci_code":"200070746","dep_code":"57","cp":"57200","id":"57200004","prix_id":"4","pop":"R","epci_name":"CA Sarreguemines Confluences","prix_maj":"2023-08-08T07:43:29Z","horaires_automate_24_24":"Non"},{"geom":[49.10011,7.05924],"prix_valeur":1.959,"reg_name":"Grand Est","com_code":"57631","dep_name":"Moselle","adresse":"60 Route de Nancy","prix_nom":"E10","com_name":"Sarreguemines","ville":"Sarreguemines","com_arm_name":"Sarreguemines","reg_code":"44","services_service":"Boutique non alimentaire//Vente de fioul domestique//Station de gonflage//Carburant additivé//Piste poids lourds//Lavage automatique//Lavage manuel//Services réparation / entretien//DAB (Distributeur automatique de billets)","com_arm_code":"57631","epci_code":"200070746","dep_code":"57","cp":"57200","id":"57200001","prix_id":"5","pop":"R","epci_name":"CA Sarreguemines Confluences","prix_maj":"2023-09-08T14:40:45Z","horaires_automate_24_24":"Non"},{"geom":[49.11719,7.10084],"prix_valeur":1.979,"reg_name":"Grand Est","com_code":"57631","dep_name":"Moselle","adresse":"Route de Bitche","prix_nom":"SP95","com_name":"Sarreguemines","ville":"SARREGUEMINES","com_arm_name":"Sarreguemines","reg_code":"44","services_service":"Toilettes publiques//Boutique alimentaire//Boutique non alimentaire//Restauration à emporter//Restauration sur place//Bar//Station de gonflage//Location de véhicule//Piste poids lourds//Espace bébé//Vente de gaz domestique (Butane, Propane)//DAB (Distributeur automatique de billets)","com_arm_code":"57631","epci_code":"200070746","dep_code":"57","cp":"57200","id":"57200004","prix_id":"2","pop":"R","epci_name":"CA Sarreguemines Confluences","prix_maj":"2023-09-04T05:54:59Z","horaires_automate_24_24":"Non"},{"geom":[49.11719,7.10084],"prix_valeur":1.929,"reg_name":"Grand Est","com_code":"57631","dep_name":"Moselle","adresse":"Route de Bitche","prix_nom":"E10","com_name":"Sarreguemines","ville":"SARREGUEMINES","com_arm_name":"Sarreguemines","reg_code":"44","services_service":"Toilettes publiques//Boutique alimentaire//Boutique non alimentaire//Restauration à emporter//Restauration sur place//Bar//Station de gonflage//Location de véhicule//Piste poids lourds//Espace bébé//Vente de gaz domestique (Butane, Propane)//DAB (Distributeur automatique de billets)","com_arm_code":"57631","epci_code":"200070746","dep_code":"57","cp":"57200","id":"57200004","prix_id":"5","pop":"R","epci_name":"CA Sarreguemines Confluences","prix_maj":"2023-09-04T05:54:59Z","horaires_automate_24_24":"Non"},{"geom":[49.11719,7.10084],"prix_valeur":2.019,"reg_name":"Grand Est","com_code":"57631","dep_name":"Moselle","adresse":"Route de Bitche","prix_nom":"SP98","com_name":"Sarreguemines","ville":"SARREGUEMINES","com_arm_name":"Sarreguemines","reg_code":"44","services_service":"Toilettes publiques//Boutique alimentaire//Boutique non alimentaire//Restauration à emporter//Restauration sur place//Bar//Station de gonflage//Location de véhicule//Piste poids lourds//Espace bébé//Vente de gaz domestique (Butane, Propane)//DAB (Distributeur automatique de billets)","com_arm_code":"57631","epci_code":"200070746","dep_code":"57","cp":"57200","id":"57200004","prix_id":"6","pop":"R","epci_name":"CA Sarreguemines Confluences","prix_maj":"2023-09-04T05:54:59Z","horaires_automate_24_24":"Non"},{"geom":[49.10655,7.07164],"reg_name":"Grand Est","prix_valeur":1.869,"com_code":"57631","dep_name":"Moselle","horaires":"{\"@automate-24-24\": \"\", \"jour\": [{\"@id\": \"1\", \"@nom\": \"Lundi\", \"@ferme\": \"\"}, {\"@id\": \"2\", \"@nom\": \"Mardi\", \"@ferme\": \"\"}, {\"@id\": \"3\", \"@nom\": \"Mercredi\", \"@ferme\": \"\"}, {\"@id\": \"4\", \"@nom\": \"Jeudi\", \"@ferme\": \"\"}, {\"@id\": \"5\", \"@nom\": \"Vendredi\", \"@ferme\": \"\"}, {\"@id\": \"6\", \"@nom\": \"Samedi\", \"@ferme\": \"\"}, {\"@id\": \"7\", \"@nom\": \"Dimanche\", \"@ferme\": \"\"}]}","adresse":"Rue Poincarré","prix_nom":"Gazole","com_name":"Sarreguemines","ville":"Sarreguemines","com_arm_name":"Sarreguemines","reg_code":"44","services_service":"Lavage manuel//Vente de gaz domestique (Butane, Propane)//DAB (Distributeur automatique de billets)","dep_code":"57","com_arm_code":"57631","epci_code":"200070746","cp":"57200","id":"57200003","prix_id":"1","epci_name":"CA Sarreguemines Confluences","pop":"R","prix_maj":"2023-09-11T10:01:53Z","horaires_automate_24_24":"Non"},{"geom":[49.10655,7.07164],"reg_name":"Grand Est","prix_valeur":0.998,"com_code":"57631","dep_name":"Moselle","horaires":"{\"@automate-24-24\": \"\", \"jour\": [{\"@id\": \"1\", \"@nom\": \"Lundi\", \"@ferme\": \"\"}, {\"@id\": \"2\", \"@nom\": \"Mardi\", \"@ferme\": \"\"}, {\"@id\": \"3\", \"@nom\": \"Mercredi\", \"@ferme\": \"\"}, {\"@id\": \"4\", \"@nom\": \"Jeudi\", \"@ferme\": \"\"}, {\"@id\": \"5\", \"@nom\": \"Vendredi\", \"@ferme\": \"\"}, {\"@id\": \"6\", \"@nom\": \"Samedi\", \"@ferme\": \"\"}, {\"@id\": \"7\", \"@nom\": \"Dimanche\", \"@ferme\": \"\"}]}","adresse":"Rue Poincarré","prix_nom":"E85","com_name":"Sarreguemines","ville":"Sarreguemines","com_arm_name":"Sarreguemines","reg_code":"44","services_service":"Lavage manuel//Vente de gaz domestique (Butane, Propane)//DAB (Distributeur automatique de billets)","dep_code":"57","com_arm_code":"57631","epci_code":"200070746","cp":"57200","id":"57200003","prix_id":"3","epci_name":"CA Sarreguemines Confluences","pop":"R","prix_maj":"2023-08-31T20:05:50Z","horaires_automate_24_24":"Non"},{"geom":[49.10011,7.05924],"prix_valeur":1.99,"reg_name":"Grand Est","com_code":"57631","dep_name":"Moselle","adresse":"60 Route de Nancy","prix_nom":"SP98","com_name":"Sarreguemines","ville":"Sarreguemines","com_arm_name":"Sarreguemines","reg_code":"44","services_service":"Boutique non alimentaire//Vente de fioul domestique//Station de gonflage//Carburant additivé//Piste poids lourds//Lavage automatique//Lavage manuel//Services réparation / entretien//DAB (Distributeur automatique de billets)","com_arm_code":"57631","epci_code":"200070746","dep_code":"57","cp":"57200","id":"57200001","prix_id":"6","pop":"R","epci_name":"CA Sarreguemines Confluences","prix_maj":"2023-09-08T14:40:45Z","horaires_automate_24_24":"Non"},{"geom":[49.114,7.074],"prix_valeur":2.019,"reg_name":"Grand Est","com_code":"57631","dep_name":"Moselle","adresse":"24 Rue du Maréchal Foch","horaires":"{\"@automate-24-24\": \"\", \"jour\": [{\"@id\": \"1\", \"@nom\": \"Lundi\", \"@ferme\": \"\"}, {\"@id\": \"2\", \"@nom\": \"Mardi\", \"@ferme\": \"\"}, {\"@id\": \"3\", \"@nom\": \"Mercredi\", \"@ferme\": \"\"}, {\"@id\": \"4\", \"@nom\": \"Jeudi\", \"@ferme\": \"\"}, {\"@id\": \"5\", \"@nom\": \"Vendredi\", \"@ferme\": \"\"}, {\"@id\": \"6\", \"@nom\": \"Samedi\", \"@ferme\": \"\"}, {\"@id\": \"7\", \"@nom\": \"Dimanche\", \"@ferme\": \"\"}]}","prix_nom":"SP98","com_name":"Sarreguemines","ville":"Sarreguemines","com_arm_name":"Sarreguemines","reg_code":"44","com_arm_code":"57631","epci_code":"200070746","dep_code":"57","cp":"57200","id":"57200002","prix_id":"6","pop":"R","epci_name":"CA Sarreguemines Confluences","prix_maj":"2023-09-11T13:13:00Z","horaires_automate_24_24":"Non"},{"geom":[49.10655,7.07164],"reg_name":"Grand Est","prix_valeur":1.949,"com_code":"57631","dep_name":"Moselle","horaires":"{\"@automate-24-24\": \"\", \"jour\": [{\"@id\": \"1\", \"@nom\": \"Lundi\", \"@ferme\": \"\"}, {\"@id\": \"2\", \"@nom\": \"Mardi\", \"@ferme\": \"\"}, {\"@id\": \"3\", \"@nom\": \"Mercredi\", \"@ferme\": \"\"}, {\"@id\": \"4\", \"@nom\": \"Jeudi\", \"@ferme\": \"\"}, {\"@id\": \"5\", \"@nom\": \"Vendredi\", \"@ferme\": \"\"}, {\"@id\": \"6\", \"@nom\": \"Samedi\", \"@ferme\": \"\"}, {\"@id\": \"7\", \"@nom\": \"Dimanche\", \"@ferme\": \"\"}]}","adresse":"Rue Poincarré","prix_nom":"SP98","com_name":"Sarreguemines","ville":"Sarreguemines","com_arm_name":"Sarreguemines","reg_code":"44","services_service":"Lavage manuel//Vente de gaz domestique (Butane, Propane)//DAB (Distributeur automatique de billets)","dep_code":"57","com_arm_code":"57631","epci_code":"200070746","cp":"57200","id":"57200003","prix_id":"6","epci_name":"CA Sarreguemines Confluences","pop":"R","prix_maj":"2023-09-04T09:33:27Z","horaires_automate_24_24":"Non"},{"geom":[49.11719,7.10084],"prix_valeur":1.879,"reg_name":"Grand Est","com_code":"57631","dep_name":"Moselle","adresse":"Route de Bitche","prix_nom":"Gazole","com_name":"Sarreguemines","ville":"SARREGUEMINES","com_arm_name":"Sarreguemines","reg_code":"44","services_service":"Toilettes publiques//Boutique alimentaire//Boutique non alimentaire//Restauration à emporter//Restauration sur place//Bar//Station de gonflage//Location de véhicule//Piste poids lourds//Espace bébé//Vente de gaz domestique (Butane, Propane)//DAB (Distributeur automatique de billets)","com_arm_code":"57631","epci_code":"200070746","dep_code":"57","cp":"57200","id":"57200004","prix_id":"1","pop":"R","epci_name":"CA Sarreguemines Confluences","prix_maj":"2023-09-08T07:39:27Z","horaires_automate_24_24":"Non"},{"geom":[49.114,7.074],"prix_valeur":1.939,"reg_name":"Grand Est","com_code":"57631","dep_name":"Moselle","adresse":"24 Rue du Maréchal Foch","horaires":"{\"@automate-24-24\": \"\", \"jour\": [{\"@id\": \"1\", \"@nom\": \"Lundi\", \"@ferme\": \"\"}, {\"@id\": \"2\", \"@nom\": \"Mardi\", \"@ferme\": \"\"}, {\"@id\": \"3\", \"@nom\": \"Mercredi\", \"@ferme\": \"\"}, {\"@id\": \"4\", \"@nom\": \"Jeudi\", \"@ferme\": \"\"}, {\"@id\": \"5\", \"@nom\": \"Vendredi\", \"@ferme\": \"\"}, {\"@id\": \"6\", \"@nom\": \"Samedi\", \"@ferme\": \"\"}, {\"@id\": \"7\", \"@nom\": \"Dimanche\", \"@ferme\": \"\"}]}","prix_nom":"E10","com_name":"Sarreguemines","ville":"Sarreguemines","com_arm_name":"Sarreguemines","reg_code":"44","com_arm_code":"57631","epci_code":"200070746","dep_code":"57","cp":"57200","id":"57200002","prix_id":"5","pop":"R","epci_name":"CA Sarreguemines Confluences","prix_maj":"2023-09-11T13:13:00Z","horaires_automate_24_24":"Non"},{"geom":[49.10011,7.05924],"prix_valeur":1.969,"reg_name":"Grand Est","com_code":"57631","dep_name":"Moselle","adresse":"60 Route de Nancy","prix_nom":"Gazole","com_name":"Sarreguemines","ville":"Sarreguemines","com_arm_name":"Sarreguemines","reg_code":"44","services_service":"Boutique non alimentaire//Vente de fioul domestique//Station de gonflage//Carburant additivé//Piste poids lourds//Lavage automatique//Lavage manuel//Services réparation / entretien//DAB (Distributeur automatique de billets)","com_arm_code":"57631","epci_code":"200070746","dep_code":"57","cp":"57200","id":"57200001","prix_id":"1","pop":"R","epci_name":"CA Sarreguemines Confluences","prix_maj":"2023-09-08T14:40:44Z","horaires_automate_24_24":"Non"},{"geom":[49.11719,7.10084],"prix_valeur":0.998,"reg_name":"Grand Est","com_code":"57631","dep_name":"Moselle","adresse":"Route de Bitche","prix_nom":"E85","com_name":"Sarreguemines","ville":"SARREGUEMINES","com_arm_name":"Sarreguemines","reg_code":"44","services_service":"Toilettes publiques//Boutique alimentaire//Boutique non alimentaire//Restauration à emporter//Restauration sur place//Bar//Station de gonflage//Location de véhicule//Piste poids lourds//Espace bébé//Vente de gaz domestique (Butane, Propane)//DAB (Distributeur automatique de billets)","com_arm_code":"57631","epci_code":"200070746","dep_code":"57","cp":"57200","id":"57200004","prix_id":"3","pop":"R","epci_name":"CA Sarreguemines Confluences","prix_maj":"2023-08-08T07:43:29Z","horaires_automate_24_24":"Non"},{"geom":[49.114,7.074],"prix_valeur":1.889,"reg_name":"Grand Est","com_code":"57631","dep_name":"Moselle","adresse":"24 Rue du Maréchal Foch","horaires":"{\"@automate-24-24\": \"\", \"jour\": [{\"@id\": \"1\", \"@nom\": \"Lundi\", \"@ferme\": \"\"}, {\"@id\": \"2\", \"@nom\": \"Mardi\", \"@ferme\": \"\"}, {\"@id\": \"3\", \"@nom\": \"Mercredi\", \"@ferme\": \"\"}, {\"@id\": \"4\", \"@nom\": \"Jeudi\", \"@ferme\": \"\"}, {\"@id\": \"5\", \"@nom\": \"Vendredi\", \"@ferme\": \"\"}, {\"@id\": \"6\", \"@nom\": \"Samedi\", \"@ferme\": \"\"}, {\"@id\": \"7\", \"@nom\": \"Dimanche\", \"@ferme\": \"\"}]}","prix_nom":"Gazole","com_name":"Sarreguemines","ville":"Sarreguemines","com_arm_name":"Sarreguemines","reg_code":"44","com_arm_code":"57631","epci_code":"200070746","dep_code":"57","cp":"57200","id":"57200002","prix_id":"1","pop":"R","epci_name":"CA Sarreguemines Confluences","prix_maj":"2023-09-11T13:13:00Z","horaires_automate_24_24":"Non"},{"geom":[49.10655,7.07164],"reg_name":"Grand Est","prix_valeur":1.869,"com_code":"57631","dep_name":"Moselle","horaires":"{\"@automate-24-24\": \"\", \"jour\": [{\"@id\": \"1\", \"@nom\": \"Lundi\", \"@ferme\": \"\"}, {\"@id\": \"2\", \"@nom\": \"Mardi\", \"@ferme\": \"\"}, {\"@id\": \"3\", \"@nom\": \"Mercredi\", \"@ferme\": \"\"}, {\"@id\": \"4\", \"@nom\": \"Jeudi\", \"@ferme\": \"\"}, {\"@id\": \"5\", \"@nom\": \"Vendredi\", \"@ferme\": \"\"}, {\"@id\": \"6\", \"@nom\": \"Samedi\", \"@ferme\": \"\"}, {\"@id\": \"7\", \"@nom\": \"Dimanche\", \"@ferme\": \"\"}]}","adresse":"Rue Poincarré","prix_nom":"E10","com_name":"Sarreguemines","ville":"Sarreguemines","com_arm_name":"Sarreguemines","reg_code":"44","services_service":"Lavage manuel//Vente de gaz domestique (Butane, Propane)//DAB (Distributeur automatique de billets)","dep_code":"57","com_arm_code":"57631","epci_code":"200070746","cp":"57200","id":"57200003","prix_id":"5","epci_name":"CA Sarreguemines Confluences","pop":"R","prix_maj":"2023-09-04T09:33:27Z","horaires_automate_24_24":"Non"}]