[{"geom":[43.250036220000005,0.07205866],"prix_valeur":1.899,"reg_name":"Occitanie","com_code":"65440","dep_name":"Hautes-Pyrénées","adresse":"87 Rue Alsace Lorraine","prix_nom":"E10","com_name":"Tarbes","ville":"Tarbes","com_arm_name":"Tarbes","reg_code":"76","services_service":"Station de gonflage//Location de véhicule//Piste poids lourds//Lavage manuel//Vente de gaz domestique (Butane, Propane)//DAB (Distributeur automatique de billets)","com_arm_code":"65440","epci_code":"200069300","dep_code":"65","cp":"65000","id":"65000008","prix_id":"5","pop":"R","epci_name":"CA Tarbes-Lourdes-Pyrénées","prix_maj":"2023-03-03T07:24:34Z","horaires_automate_24_24":"Non"},{"geom":[43.23426,0.05428],"prix_valeur":1.889,"reg_name":"Occitanie","com_code":"65440","dep_name":"Hautes-Pyrénées","adresse":"Boulevard Lacaussade","prix_nom":"Gazole","com_name":"Tarbes","ville":"TARBES","com_arm_name":"Tarbes","reg_code":"76","services_service":"Vente de gaz domestique (Butane, Propane)","com_arm_code":"65440","epci_code":"200069300","dep_code":"65","cp":"65000","id":"65000009","prix_id":"1","pop":"R","epci_name":"CA Tarbes-Lourdes-Pyrénées","prix_maj":"2023-02-11T09:07:38Z","horaires_automate_24_24":"Non"},{"geom":[43.223,0.058],"prix_valeur":1.973,"reg_name":"Occitanie","com_code":"65440","dep_name":"Hautes-Pyrénées","adresse":"BD DE LATTRE DE TASSIGNY","horaires":"{\"@automate-24-24\": \"\", \"jour\": [{\"@id\": \"1\", \"@nom\": \"Lundi\", \"@ferme\": \"\"}, {\"@id\": \"2\", \"@nom\": \"Mardi\", \"@ferme\": \"\"}, {\"@id\": \"3\", \"@nom\": \"Mercredi\", \"@ferme\": \"\"}, {\"@id\": \"4\", \"@nom\": \"Jeudi\", \"@ferme\": \"\"}, {\"@id\": \"5\", \"@nom\": \"Vendredi\", \"@ferme\": \"\"}, {\"@id\": \"6\", \"@nom\": \"Samedi\", \"@ferme\": \"\"}, {\"@id\": \"7\", \"@nom\": \"Dimanche\", \"@ferme\": \"\"}]}","prix_nom":"SP98","com_name":"Tarbes","ville":"Tarbes","com_arm_name":"Tarbes","reg_code":"76","com_arm_code":"65440","epci_code":"200069300","dep_code":"65","cp":"65000","id":"65000004","prix_id":"6","pop":"R","epci_name":"CA Tarbes-Lourdes-Pyrénées","prix_maj":"2023-03-03T03:01:00Z","horaires_automate_24_24":"Non"}]