[{"geom":[48.73996641,2.77658058],"prix_valeur":1.809,"reg_name":"Île-de-France","com_code":"77470","dep_name":"Seine-et-Marne","adresse":"RUE DE LA LIBERATION","prix_nom":"SP98","com_name":"Tournan-en-Brie","ville":"Tournan-en-Brie","com_arm_name":"Tournan-en-Brie","reg_code":"11","services_service":"Lavage manuel","com_arm_code":"77470","epci_code":"200023125","dep_code":"77","cp":"77220","id":"77220005","prix_id":"6","pop":"R","epci_name":"CC Les Portes Briardes entre Villes et Forêts","prix_maj":"2023-11-20T13:11:45Z","horaires_automate_24_24":"Non"},{"geom":[48.73824,2.77365],"reg_name":"Île-de-France","com_code":"77470","dep_name":"Seine-et-Marne","adresse":"Route de la Libération","com_name":"Tournan-en-Brie","ville":"Tournan-en-Brie","com_arm_name":"Tournan-en-Brie","reg_code":"11","services_service":"Vente de gaz domestique (Butane, Propane)//DAB (Distributeur automatique de billets)","com_arm_code":"77470","epci_code":"200023125","dep_code":"77","cp":"77220","id":"77220001","pop":"R","epci_name":"CC Les Portes Briardes entre Villes et Forêts","horaires_automate_24_24":"Non"},{"geom":[48.73996641,2.77658058],"prix_valeur":1.759,"reg_name":"Île-de-France","com_code":"77470","dep_name":"Seine-et-Marne","adresse":"RUE DE LA LIBERATION","prix_nom":"E10","com_name":"Tournan-en-Brie","ville":"Tournan-en-Brie","com_arm_name":"Tournan-en-Brie","reg_code":"11","services_service":"Lavage manuel","com_arm_code":"77470","epci_code":"200023125","dep_code":"77","cp":"77220","id":"77220005","prix_id":"5","pop":"R","epci_name":"CC Les Portes Briardes entre Villes et Forêts","prix_maj":"2023-11-20T13:11:45Z","horaires_automate_24_24":"Non"},{"geom":[48.73996641,2.77658058],"prix_valeur":1.779,"reg_name":"Île-de-France","com_code":"77470","dep_name":"Seine-et-Marne","adresse":"RUE DE LA LIBERATION","prix_nom":"Gazole","com_name":"Tournan-en-Brie","ville":"Tournan-en-Brie","com_arm_name":"Tournan-en-Brie","reg_code":"11","services_service":"Lavage manuel","com_arm_code":"77470","epci_code":"200023125","dep_code":"77","cp":"77220","id":"77220005","prix_id":"1","pop":"R","epci_name":"CC Les Portes Briardes entre Villes et Forêts","prix_maj":"2023-11-20T13:11:45Z","horaires_automate_24_24":"Non"},{"geom":[48.73996641,2.77658058],"prix_valeur":1.019,"reg_name":"Île-de-France","com_code":"77470","dep_name":"Seine-et-Marne","adresse":"RUE DE LA LIBERATION","prix_nom":"E85","com_name":"Tournan-en-Brie","ville":"Tournan-en-Brie","com_arm_name":"Tournan-en-Brie","reg_code":"11","services_service":"Lavage manuel","com_arm_code":"77470","epci_code":"200023125","dep_code":"77","cp":"77220","id":"77220005","prix_id":"3","pop":"R","epci_name":"CC Les Portes Briardes entre Villes et Forêts","prix_maj":"2023-11-20T07:59:06Z","horaires_automate_24_24":"Non"}]