[{"geom":[48.84251,-0.71187],"prix_valeur":1.799,"reg_name":"Normandie","com_code":"14726","dep_name":"Calvados","adresse":"Lieu-dit La Barbairie","prix_nom":"SP95","com_name":"Valdallière","ville":"Vassy","com_arm_name":"Valdallière","reg_code":"28","services_service":"DAB (Distributeur automatique de billets)","com_arm_code":"14726","epci_code":"200068799","dep_code":"14","cp":"14410","id":"14410002","prix_id":"2","pop":"R","epci_name":"CC Intercom de la Vire au Noireau","prix_maj":"2024-01-06T10:50:38Z","horaires_automate_24_24":"Non","name":"CARREFOUR CONTACT","brand":"Carrefour Contact","shortage":["GPLc","SP98"]},{"geom":[48.84251,-0.71187],"prix_valeur":1.749,"reg_name":"Normandie","com_code":"14726","dep_name":"Calvados","adresse":"Lieu-dit La Barbairie","prix_nom":"Gazole","com_name":"Valdallière","ville":"Vassy","com_arm_name":"Valdallière","reg_code":"28","services_service":"DAB (Distributeur automatique de billets)","com_arm_code":"14726","epci_code":"200068799","dep_code":"14","cp":"14410","id":"14410002","prix_id":"1","pop":"R","epci_name":"CC Intercom de la Vire au Noireau","prix_maj":"2024-01-03T09:52:06Z","horaires_automate_24_24":"Non","name":"CARREFOUR CONTACT","brand":"Carrefour Contact","shortage":["GPLc","SP98"]},{"geom":[48.84251,-0.71187],"prix_valeur":1.777,"reg_name":"Normandie","com_code":"14726","dep_name":"Calvados","adresse":"Lieu-dit La Barbairie","prix_nom":"E10","com_name":"Valdallière","ville":"Vassy","com_arm_name":"Valdallière","reg_code":"28","services_service":"DAB (Distributeur automatique de billets)","com_arm_code":"14726","epci_code":"200068799","dep_code":"14","cp":"14410","id":"14410002","prix_id":"5","pop":"R","epci_name":"CC Intercom de la Vire au Noireau","prix_maj":"2024-01-06T10:50:38Z","horaires_automate_24_24":"Non","name":"CARREFOUR CONTACT","brand":"Carrefour Contact","shortage":["GPLc","SP98"]}]