[{"geom":[48.16057,6.45091],"prix_valeur":1.949,"reg_name":"Grand Est","com_code":"88160","dep_name":"Vosges","adresse":"30 Rue de Remiremont","prix_nom":"SP98","com_name":"Épinal","ville":"ÉPINAL","com_arm_name":"Épinal","reg_code":"44","services_service":"Carburant additivé//Vente de gaz domestique (Butane, Propane)//DAB (Distributeur automatique de billets)","com_arm_code":"88160","epci_code":"200068757","dep_code":"88","cp":"88000","id":"88000001","prix_id":"6","pop":"R","epci_name":"CA d'Épinal","prix_maj":"2023-03-24T08:13:53Z","horaires_automate_24_24":"Non"},{"geom":[48.16057,6.45091],"prix_valeur":1.849,"reg_name":"Grand Est","com_code":"88160","dep_name":"Vosges","adresse":"30 Rue de Remiremont","prix_nom":"Gazole","com_name":"Épinal","ville":"ÉPINAL","com_arm_name":"Épinal","reg_code":"44","services_service":"Carburant additivé//Vente de gaz domestique (Butane, Propane)//DAB (Distributeur automatique de billets)","com_arm_code":"88160","epci_code":"200068757","dep_code":"88","cp":"88000","id":"88000001","prix_id":"1","pop":"R","epci_name":"CA d'Épinal","prix_maj":"2023-03-24T08:13:52Z","horaires_automate_24_24":"Non"},{"geom":[48.16057,6.45091],"prix_valeur":0.949,"reg_name":"Grand Est","com_code":"88160","dep_name":"Vosges","adresse":"30 Rue de Remiremont","prix_nom":"GPLc","com_name":"Épinal","ville":"ÉPINAL","com_arm_name":"Épinal","reg_code":"44","services_service":"Carburant additivé//Vente de gaz domestique (Butane, Propane)//DAB (Distributeur automatique de billets)","com_arm_code":"88160","epci_code":"200068757","dep_code":"88","cp":"88000","id":"88000001","prix_id":"4","pop":"R","epci_name":"CA d'Épinal","prix_maj":"2023-03-24T08:13:53Z","horaires_automate_24_24":"Non"},{"geom":[48.18685,6.44195],"prix_valeur":1.904,"reg_name":"Grand Est","com_code":"88160","dep_name":"Vosges","adresse":"2 Avenue de la Fontenelle","prix_nom":"SP95","com_name":"Épinal","ville":"Épinal","com_arm_name":"Épinal","reg_code":"44","services_service":"Vente de gaz domestique (Butane, Propane)","com_arm_code":"88160","epci_code":"200068757","dep_code":"88","cp":"88000","id":"88000007","prix_id":"2","pop":"R","epci_name":"CA d'Épinal","prix_maj":"2023-03-23T09:28:03Z","horaires_automate_24_24":"Non"},{"geom":[48.18517,6.47047],"prix_valeur":1.86,"reg_name":"Grand Est","com_code":"88160","dep_name":"Vosges","adresse":"Avenue de Saint-Dié","prix_nom":"Gazole","com_name":"Épinal","ville":"Épinal","com_arm_name":"Épinal","reg_code":"44","services_service":"Vente de gaz domestique (Butane, Propane)//DAB (Distributeur automatique de billets)","com_arm_code":"88160","epci_code":"200068757","dep_code":"88","cp":"88000","id":"88000002","prix_id":"1","pop":"R","epci_name":"CA d'Épinal","prix_maj":"2023-03-07T14:04:56Z","horaires_automate_24_24":"Non"},{"geom":[48.18517,6.47047],"prix_valeur":1.965,"reg_name":"Grand Est","com_code":"88160","dep_name":"Vosges","adresse":"Avenue de Saint-Dié","prix_nom":"SP95","com_name":"Épinal","ville":"Épinal","com_arm_name":"Épinal","reg_code":"44","services_service":"Vente de gaz domestique (Butane, Propane)//DAB (Distributeur automatique de billets)","com_arm_code":"88160","epci_code":"200068757","dep_code":"88","cp":"88000","id":"88000002","prix_id":"2","pop":"R","epci_name":"CA d'Épinal","prix_maj":"2023-03-13T09:45:10Z","horaires_automate_24_24":"Non"},{"geom":[48.18685,6.44195],"prix_valeur":1.825,"reg_name":"Grand Est","com_code":"88160","dep_name":"Vosges","adresse":"2 Avenue de la Fontenelle","prix_nom":"Gazole","com_name":"Épinal","ville":"Épinal","com_arm_name":"Épinal","reg_code":"44","services_service":"Vente de gaz domestique (Butane, Propane)","com_arm_code":"88160","epci_code":"200068757","dep_code":"88","cp":"88000","id":"88000007","prix_id":"1","pop":"R","epci_name":"CA d'Épinal","prix_maj":"2023-03-23T09:28:02Z","horaires_automate_24_24":"Non"},{"geom":[48.18517,6.47047],"prix_valeur":1.97,"reg_name":"Grand Est","com_code":"88160","dep_name":"Vosges","adresse":"Avenue de Saint-Dié","prix_nom":"SP98","com_name":"Épinal","ville":"Épinal","com_arm_name":"Épinal","reg_code":"44","services_service":"Vente de gaz domestique (Butane, Propane)//DAB (Distributeur automatique de billets)","com_arm_code":"88160","epci_code":"200068757","dep_code":"88","cp":"88000","id":"88000002","prix_id":"6","pop":"R","epci_name":"CA d'Épinal","prix_maj":"2023-03-21T08:35:23Z","horaires_automate_24_24":"Non"},{"geom":[48.16057,6.45091],"prix_valeur":1.849,"reg_name":"Grand Est","com_code":"88160","dep_name":"Vosges","adresse":"30 Rue de Remiremont","prix_nom":"E10","com_name":"Épinal","ville":"ÉPINAL","com_arm_name":"Épinal","reg_code":"44","services_service":"Carburant additivé//Vente de gaz domestique (Butane, Propane)//DAB (Distributeur automatique de billets)","com_arm_code":"88160","epci_code":"200068757","dep_code":"88","cp":"88000","id":"88000001","prix_id":"5","pop":"R","epci_name":"CA d'Épinal","prix_maj":"2023-03-24T08:13:53Z","horaires_automate_24_24":"Non"},{"geom":[48.18685,6.44195],"prix_valeur":1.839,"reg_name":"Grand Est","com_code":"88160","dep_name":"Vosges","adresse":"2 Avenue de la Fontenelle","prix_nom":"E10","com_name":"Épinal","ville":"Épinal","com_arm_name":"Épinal","reg_code":"44","services_service":"Vente de gaz domestique (Butane, Propane)","com_arm_code":"88160","epci_code":"200068757","dep_code":"88","cp":"88000","id":"88000007","prix_id":"5","pop":"R","epci_name":"CA d'Épinal","prix_maj":"2023-03-23T09:28:03Z","horaires_automate_24_24":"Non"},{"geom":[48.18685,6.44195],"prix_valeur":1.929,"reg_name":"Grand Est","com_code":"88160","dep_name":"Vosges","adresse":"2 Avenue de la Fontenelle","prix_nom":"SP98","com_name":"Épinal","ville":"Épinal","com_arm_name":"Épinal","reg_code":"44","services_service":"Vente de gaz domestique (Butane, Propane)","com_arm_code":"88160","epci_code":"200068757","dep_code":"88","cp":"88000","id":"88000007","prix_id":"6","pop":"R","epci_name":"CA d'Épinal","prix_maj":"2023-03-23T09:28:03Z","horaires_automate_24_24":"Non"}]